cpu/cpu.v
module cpu (clk, reset, from_memory, memory_operation, memory_address, to_memory);

initial begin
    $display("************** CPU **********");
end

  input clk;
  input reset;
  input [7:0] from_memory;

  output reg memory_operation;
  output reg [7:0] memory_address;
  output reg [7:0] to_memory;

  reg [7:0] instruction;
  reg [7:0] target;

  reg [7:0] status;
  reg [7:0] ip;

  reg [7:0] general_reg[7:0];

  always @(reset) begin
    status <= 0;
    ip <= 0;
    memory_operation <= 0;
    memory_address <= 0;
    to_memory <= 0;
  end

  always @(posedge clk) begin
      case(status)
        8'b00000000: begin
          $display("starting instruction process");
          memory_operation <= 0;
          memory_address <= ip;
          status <= status + 1;
        end
        8'b00000001: begin
          $display("copying instruction content");
          instruction <= from_memory;
          status <= status + 1;
        end
        8'b00000010: begin
          $display("reding target value ");
          memory_operation <= 0;
          memory_address <= ip + 1;
          status <= status + 1;
        end
        8'b00000011: begin
          $display("copying target value ");
          target <= from_memory;
          status <= status + 1;
        end
        8'b00000100: begin
          //moving the ip to next instruction:
          ip <= ip + 2;
          $display(" got the instruction: %b with target: %b (%0d)", instruction, target, target);
          case (instruction[7:4])
            4'b0001: begin
              $display("moving scalar data to reg");
              general_reg[instruction[3:0]] <= target;
              status <= 0;
            end
            4'b0010: begin
              $display("moving data from memory to from_memory reg");
              memory_operation <= 0 ;
              memory_address <= target;

              status <= status + 1;
            end
            4'b1111: begin
              $display("get exit signal from instruction");
              status <= 8'b11111111;
            end
           endcase
        end
        8'b00000101: begin
          case (instruction[7:4])
            4'b0010: begin
              $display("moving data from from_memory reg to target reg");
              $display("The value in from_memory is now %0d", from_memory);
              general_reg[instruction[3:0]] <= from_memory;
              status <= 0;
            end
          endcase
        end
        8'b11111111: begin
          $display("end of the program, nothing happen from now");
          $display("General Reg: %b  %b", general_reg[0], general_reg[1]);
        end
        default: begin
          $display("end of life, nothing happen");
        end
      endcase
    end
   
endmodule

cpu/memory.v
module memory (clk, input_address, operation, input_value, output_value);

initial begin
    $display("************** memory **********");
end

  input clk;
  input [7:0] input_address;
  input operation; 
  input [7:0] input_value;
  output reg [7:0] output_value;
  
  reg [7:0] mem[0:99];
 
  initial begin
   $readmemb ("ram.patt", mem); 
  end

  always @(negedge clk) begin
  
  if (operation) 
    mem[input_address] <= input_value;
  else
    output_value <= mem[input_address];

  end

 // begin
 //   if (operation == 'b0)
 //   begin
 //       output_value <= mem[0] ;
 //     end
 //   else
 //   begin
 //       mem[input_address] <= input_value; 
 //     end
 // end

endmodule

cpu/cpu_tb.v
    `timescale 1ns/1ns  
    module cpu_test;  
      
        /*Make a reset that pulses once.*/  
        reg reset = 0;  

         initial  
            begin  
                #1 reset = 1;  
                #2 reset = 0;  
                #400 $stop;  
            end  
     
          
        reg clk = 0;  
        always #5 clk = !clk;  
          
        wire [7:0] memory_value;  
        wire operation;
        wire [7:0] memory_address;
        wire [7:0] memory_input;

        memory u_memory (clk, memory_address, operation, memory_input, memory_value);  

        cpu u_cpu(clk, reset, memory_value, operation, memory_address, memory_input);
          
        initial  
            $monitor("At time %t, value = %h (%0d), clk = %h(%0d)",$time, memory_value, memory_value, clk, clk);  

				initial
						begin

							$dumpfile("cpu_test.vcd");
							$dumpvars(0, u_cpu);
						end

    endmodule  
    //test

cpu/cpu_test.vcd
$date
	Fri May 12 00:05:22 2017
$end
$version
	Icarus Verilog
$end
$timescale
	1ns
$end
$scope module cpu_test $end
$scope module u_cpu $end
$var wire 1 ! clk $end
$var wire 1 " reset $end
$var wire 8 # from_memory [7:0] $end
$var reg 8 $ instruction [7:0] $end
$var reg 8 % ip [7:0] $end
$var reg 8 & memory_address [7:0] $end
$var reg 1 ' memory_operation $end
$var reg 8 ( status [7:0] $end
$var reg 8 ) target [7:0] $end
$var reg 8 * to_memory [7:0] $end
$upscope $end
$upscope $end
$enddefinitions $end
#0
$dumpvars
b0 *
bx )
b0 (
0'
b0 &
b0 %
bx $
bx #
0"
0!
$end
#1
1"
#3
0"
#5
b1 (
1!
#10
b10000 #
0!
#15
b10 (
b10000 $
1!
#20
0!
#25
b11 (
b1 &
1!
#30
b1000110 #
0!
#35
b100 (
b1000110 )
1!
#40
0!
#45
b0 (
b10 %
1!
#50
0!
#55
b1 (
b10 &
1!
#60
b100001 #
0!
#65
b10 (
b100001 $
1!
#70
0!
#75
b11 (
b11 &
1!
#80
b10000 #
0!
#85
b100 (
b10000 )
1!
#90
0!
#95
b101 (
b10000 &
b100 %
1!
#100
b1110 #
0!
#105
b0 (
1!
#110
0!
#115
b1 (
b100 &
1!
#120
b11110000 #
0!
#125
b10 (
b11110000 $
1!
#130
0!
#135
b11 (
b101 &
1!
#140
b0 #
0!
#145
b100 (
b0 )
1!
#150
0!
#155
b11111111 (
b110 %
1!
