cpu/memory.v
module memory (clk, input_address, operation, input_value, output_value);

initial begin
    $display("************** memory **********");
end

  input clk;
  input [7:0] input_address;
  input operation; 
  input [7:0] input_value;
  output reg [7:0] output_value;
  
  reg [7:0] mem[0:99];
 
  initial begin
   $readmemb ("ram.patt", mem); 
  end

  always @(negedge clk) begin
  
  if (operation) 
    mem[input_address] <= input_value;
  else
    output_value <= mem[input_address];

  end

 // begin
 //   if (operation == 'b0)
 //   begin
 //       output_value <= mem[0] ;
 //     end
 //   else
 //   begin
 //       mem[input_address] <= input_value; 
 //     end
 // end

endmodule

cpu/memory_tb.v
    `timescale 1ns/1ns  
    module test;  
      
        /*Make a reset that pulses once.*/  
        reg reset = 0;  
        reg [7:0] input_address = 9;
        reg operation = 0;
        reg [7:0] input_value = 12;
          
        initial  
            begin  
    //            #1 operation = 1;
     //           #2 input_value = 13;
                #10 operation = 0;

                //#19 operation = 0;
                #28 operation = 1;
                #29 input_value = 7;

                #35 operation = 0;

                #58 operation = 1;
                #59 input_value = 8;

                #69 operation = 0;

                #100 $stop;  
            end  
          
        /*Make a regular pulsing closk*/  
          
        reg clk = 0;  
        always #5 clk = !clk;  
          
        wire [7:0] value;  
        memory u_memory (clk, input_address, operation, input_value, value);  
          
        initial  
            $monitor("At time %t, value = %h (%0d), clk = %h(%0d)",$time, value, value, clk, clk);  

				initial
						begin

							$dumpfile("memory_test.vcd");
							$dumpvars(0, u_memory);
						end

    endmodule  
    //test

cpu/memory_test.vcd
$date
	Thu May 11 16:43:51 2017
$end
$version
	Icarus Verilog
$end
$timescale
	1ns
$end
$scope module test $end
$scope module u_memory $end
$var wire 1 ! clk $end
$var wire 8 " input_address [7:0] $end
$var wire 8 # input_value [7:0] $end
$var wire 1 $ operation $end
$var reg 8 % output_value [7:0] $end
$upscope $end
$upscope $end
$enddefinitions $end
#0
$dumpvars
bx %
0$
b1100 #
b1001 "
0!
$end
#5
b100 %
1!
#10
0!
#15
1!
#20
0!
#25
1!
#30
0!
#35
1!
#38
1$
#40
0!
#45
1!
#50
0!
#55
1!
#60
0!
#65
1!
#67
b111 #
#70
0!
#75
1!
#80
0!
#85
1!
#90
0!
#95
1!
#100
0!
#102
0$
#105
b111 %
1!
#110
0!
#115
1!
#120
0!
#125
1!
#130
0!
#135
1!
#140
0!
#145
1!
#150
0!
#155
1!
#160
0!
1$
#165
1!
#170
0!
#175
1!
#180
0!
#185
1!
#190
0!
#195
1!
#200
0!
#205
1!
#210
0!
#215
1!
#219
b1000 #
#220
0!
#225
1!
#230
0!
#235
1!
#240
0!
#245
1!
#250
0!
#255
1!
#260
0!
#265
1!
#270
0!
#275
1!
#280
0!
#285
1!
#288
0$
#290
0!
#295
b1000 %
1!
