first_sample/basic_gate.v
module not_gate (input_value, output_value);

initial begin
    $display("*************************");
    $display("not_gate");
    $display("*************************");
end

  input input_value;
  output output_value;
  
  assign output_value = !input_value ;

endmodule


module and_gate (input_a, input_b, output_value);

initial begin
    $display("*************************");
    $display("and_gate");
    $display("*************************");
end

  input input_a;
  input input_b;
  output output_value;

  // assign output_value = input_a & input_b;
  and u_and (output_value, input_a, input_b);

endmodule

first_sample/basic_gate_tb.v
   `timescale 1ns/1ns  
    module test;  
      
        /*Make a reset that pulses once.*/  
        reg reset = 0;  
          
        initial  
            begin  
                #17 reset = 1;  
                #11 reset = 0;  
                #29 reset = 1;  
                #11 reset = 0;  
                #100 $stop;  
            end  
          
        /*Make a regular pulsing closk*/  
          
        reg clk = 0;  
        reg clk_double = 0;

        always #5 clk = !clk;
        always #10 clk_double = !clk_double;  
          
        wire not_value;  
        not_gate not_g (clk, not_value);

        wire and_value;
        and_gate and_g(clk, clk_double, and_value);  
          
        initial  
          begin
            $monitor("At time %t, and_value = %h (%0d), clk = %h(%0d)",$time, and_value, and_value, clk, clk);  
          end

				initial
						begin

							$dumpfile("gate_test.vcd");
							$dumpvars(0, not_g);
              $dumpvars(0, and_g);
						end

    endmodule  
    //test

first_sample/gate_test.vcd
$date
	Wed May 10 17:01:37 2017
$end
$version
	Icarus Verilog
$end
$timescale
	1ns
$end
$scope module test $end
$scope module not_g $end
$var wire 1 ! input_value $end
$var wire 1 " output_value $end
$upscope $end
$upscope $end
$scope module test $end
$scope module and_g $end
$var wire 1 ! input_a $end
$var wire 1 # input_b $end
$var wire 1 $ output_value $end
$upscope $end
$upscope $end
$enddefinitions $end
#0
$dumpvars
0$
0#
1"
0!
$end
#5
0"
1!
#10
1"
0!
1#
#15
1$
0"
1!
#20
0$
1"
0!
0#
#25
0"
1!
#30
1"
0!
1#
#35
1$
0"
1!
#40
0$
1"
0!
0#
#45
0"
1!
#50
1"
0!
1#
#55
1$
0"
1!
#60
0$
1"
0!
0#
#65
0"
1!
#70
1"
0!
1#
#75
1$
0"
1!
#80
0$
1"
0!
0#
#85
0"
1!
#90
1"
0!
1#
#95
1$
0"
1!
#100
0$
1"
0!
0#
#105
0"
1!
#110
1"
0!
1#
#115
1$
0"
1!
#120
0$
1"
0!
0#
#125
0"
1!
#130
1"
0!
1#
#135
1$
0"
1!
#140
0$
1"
0!
0#
#145
0"
1!
#150
1"
0!
1#
#155
1$
0"
1!
#160
0$
1"
0!
0#
#165
0"
1!
