first_sample/latch.v
module rs_latch (input_a, input_b, output_value);

initial begin
    $display("*************************");
    $display("rs_latch");
    $display("*************************");
end

  input input_a;
  input input_b;
  output output_value;

  wire nor_a;
  wire nor_b;

  nor u1 (nor_a, input_a, nor_b);
  nor u2 (nor_b, input_b, nor_a);

  assign output_value = nor_a;


endmodule

first_sample/latch_tb.v
   `timescale 1ns/1ns  
    module test;  
      
        /*Make a reset that pulses once.*/  
        reg reset = 0;  
          
        initial  
            begin  
                #17 reset = 1;  
                #11 reset = 0;  
                #29 reset = 1;  
                #11 reset = 0;  
                #100 $stop;  
            end  
          
        /*Make a regular pulsing closk*/  
          
        reg clk = 0;  
        reg clk_double = 0;

        always #5 clk = !clk;
        always #10 clk_double = !clk_double;  
          
        wire latch_value;  
        rs_latch u_rs_latch(clk, clk_double, latch_value);
          
        initial  
          begin
            $monitor("At time %t, latch_value = %h (%0d), clk = %h(%0d)",$time, latch_value, latch_value, clk, clk);  
          end

				initial
						begin

							$dumpfile("latch_test.vcd");
							$dumpvars(0, u_rs_latch);
						end

    endmodule  
    //test

first_sample/latch_test.vcd
$date
	Wed May 10 17:22:09 2017
$end
$version
	Icarus Verilog
$end
$timescale
	1ns
$end
$scope module test $end
$scope module u_rs_latch $end
$var wire 1 ! input_a $end
$var wire 1 " input_b $end
$var wire 1 # nor_a $end
$var wire 1 $ nor_b $end
$var wire 1 % output_value $end
$upscope $end
$upscope $end
$enddefinitions $end
#0
$dumpvars
x%
x$
x#
0"
0!
$end
#5
1$
0%
0#
1!
#10
1%
1#
0$
0!
1"
#15
0%
0#
1!
#20
1$
0!
0"
#25
1!
#30
1%
1#
0$
0!
1"
#35
0%
0#
1!
#40
1$
0!
0"
#45
1!
#50
1%
1#
0$
0!
1"
#55
0%
0#
1!
#60
1$
0!
0"
#65
1!
#70
1%
1#
0$
0!
1"
#75
0%
0#
1!
#80
1$
0!
0"
#85
1!
#90
1%
1#
0$
0!
1"
#95
0%
0#
1!
#100
1$
0!
0"
#105
1!
#110
1%
1#
0$
0!
1"
#115
0%
0#
1!
#120
1$
0!
0"
#125
1!
#130
1%
1#
0$
0!
1"
#135
0%
0#
1!
#140
1$
0!
0"
#145
1!
#150
1%
1#
0$
0!
1"
#155
0%
0#
1!
#160
1$
0!
0"
#165
1!
